LICENSE
README.md
setup.cfg
setup.py
tkinterplus/SpriteSheet.py
tkinterplus/__init__.py
tkinterplus/constants.py
tkinterplus/format.py
tkinterplus/modalbox.py
tkinterplus/modaldialog.py
tkinterplus/simplemodal.py
tkinterplus/util.py
tkinterplus.egg-info/PKG-INFO
tkinterplus.egg-info/SOURCES.txt
tkinterplus.egg-info/dependency_links.txt
tkinterplus.egg-info/requires.txt
tkinterplus.egg-info/top_level.txt
tkinterplus/experimental_widgets/audio.py
tkinterplus/experimental_widgets/canvas3d.py
tkinterplus/experimental_widgets/codeblock.py
tkinterplus/experimental_widgets/formattext.py
tkinterplus/experimental_widgets/paragraph.py
tkinterplus/experimental_widgets/slideshow.py
tkinterplus/experimental_widgets/tabs.py
tkinterplus/experimental_widgets/tooltip.py
tkinterplus/widgets/accordion.py
tkinterplus/widgets/context_menu.py
tkinterplus/widgets/footer.py
tkinterplus/widgets/form.py
tkinterplus/widgets/input.py
tkinterplus/widgets/modal.py
tkinterplus/widgets/picture.py
tkinterplus/widgets/scrolledframe.py
tkinterplus/windows/askenum.py
tkinterplus/windows/config.py
tkinterplus/windows/showprogress.py
tkinterplus/windows/texteditor.py